{"skeleton":{"hash":"dh5B6a7ddVjQo0lgIKHA+noZzXo","spine":"3.6.53","width":0,"height":0,"images":"./images/"},"bones":[{"name":"root"},{"name":"Ef_smoke_g","parent":"root","scaleX":1.5,"scaleY":1.5},{"name":"im_024_1","parent":"Ef_smoke_g","length":60.83,"rotation":90,"scaleX":1.2,"scaleY":1.2},{"name":"im_024_2","parent":"Ef_smoke_g","length":60.83,"rotation":90,"scaleX":0.9,"scaleY":0.9},{"name":"im_024_3","parent":"Ef_smoke_g","length":60.83,"rotation":90,"scaleX":0.6,"scaleY":0.6},{"name":"im_024_4","parent":"Ef_smoke_g","length":60.83,"rotation":90,"scaleX":0.6,"scaleY":0.6}],"slots":[{"name":"im_024_1","bone":"im_024_1"},{"name":"im_024_2","bone":"im_024_2"},{"name":"im_024_3","bone":"im_024_3"},{"name":"im_024_4","bone":"im_024_4"}],"skins":{"default":{"im_024_1":{"im_024_2":{"x":35.1,"rotation":-90,"width":103,"height":135}},"im_024_2":{"im_024_2":{"x":35.1,"rotation":-90,"width":103,"height":135}},"im_024_3":{"im_024_2":{"x":35.1,"rotation":-90,"width":103,"height":135}},"im_024_4":{"im_024_2":{"x":35.1,"rotation":-90,"width":103,"height":135}}}},"animations":{"Action":{"slots":{"im_024_1":{"color":[{"time":0,"color":"ff000000","curve":[0.352,0.02,0.684,1]},{"time":0.2333,"color":"ffcc7bff","curve":[0.343,0.02,0.676,0.51]},{"time":0.4333,"color":"ffffffff","curve":[0.352,0.02,0.684,1]},{"time":0.8333,"color":"ffffff00"}],"attachment":[{"time":0,"name":"im_024_2"},{"time":1.3333,"name":null}]},"im_024_2":{"color":[{"time":0.1,"color":"ffffff00","curve":[0.338,0.03,0.671,0.43]},{"time":0.4333,"color":"ffffffff","curve":[0.347,0.34,0.68,1]},{"time":1.4333,"color":"ffffff00"}],"attachment":[{"time":0.1,"name":"im_024_2"},{"time":1.4333,"name":null}]},"im_024_3":{"color":[{"time":0.2,"color":"ffffff00","curve":[0.338,0.03,0.671,0.43]},{"time":0.5333,"color":"ffd96aff","curve":[0.347,0.34,0.68,1]},{"time":1.5333,"color":"ffffff00"}],"attachment":[{"time":0.2,"name":"im_024_2"},{"time":1.5333,"name":null}]},"im_024_4":{"color":[{"time":0.2667,"color":"ffffff00","curve":[0.338,0.03,0.671,0.43]},{"time":0.5667,"color":"ffffffff","curve":[0.347,0.34,0.68,1]},{"time":1.6,"color":"ffffff00"}],"attachment":[{"time":0.2667,"name":"im_024_2"},{"time":1.6,"name":null}]}},"bones":{"im_024_1":{"rotate":[{"time":0,"angle":0,"curve":"stepped"},{"time":1.3333,"angle":0}],"translate":[{"time":0,"x":0,"y":0,"curve":"stepped"},{"time":1.3333,"x":0,"y":0}],"scale":[{"time":0,"x":1,"y":1,"curve":[0.352,0.02,0.684,1]},{"time":1.3333,"x":3.5,"y":4.333}],"shear":[{"time":0,"x":0,"y":0,"curve":"stepped"},{"time":1.3333,"x":0,"y":0}]},"im_024_2":{"rotate":[{"time":0.1,"angle":0,"curve":"stepped"},{"time":1.4333,"angle":0}],"translate":[{"time":0.1,"x":0,"y":0,"curve":"stepped"},{"time":1.4333,"x":0,"y":0}],"scale":[{"time":0.1,"x":1,"y":1,"curve":[0.352,0.02,0.684,1]},{"time":1.4333,"x":4.333,"y":5.444}],"shear":[{"time":0.1,"x":0,"y":0,"curve":"stepped"},{"time":1.4333,"x":0,"y":0}]},"im_024_3":{"rotate":[{"time":0.2,"angle":0,"curve":"stepped"},{"time":1.5333,"angle":0}],"translate":[{"time":0.2,"x":0,"y":0,"curve":"stepped"},{"time":1.5333,"x":0,"y":0}],"scale":[{"time":0.2,"x":1,"y":1,"curve":[0.352,0.02,0.684,1]},{"time":1.5333,"x":6,"y":7.667}],"shear":[{"time":0.2,"x":0,"y":0,"curve":"stepped"},{"time":1.5333,"x":0,"y":0}]},"im_024_4":{"rotate":[{"time":0.2667,"angle":0,"curve":"stepped"},{"time":1.6,"angle":0}],"translate":[{"time":0.2667,"x":0,"y":0,"curve":"stepped"},{"time":1.6,"x":0,"y":0}],"scale":[{"time":0.2667,"x":1,"y":1,"curve":[0.352,0.02,0.684,1]},{"time":1.6,"x":6,"y":7.667}],"shear":[{"time":0.2667,"x":0,"y":0,"curve":"stepped"},{"time":1.6,"x":0,"y":0}]}}}}}